odoo8_addon_website_product_share-8.0.1.0.0.99.dev10-nspkg.pth
odoo_addons/website_product_share/README.rst
odoo_addons/website_product_share/__init__.py
odoo_addons/website_product_share/__openerp__.py
odoo_addons/website_product_share/i18n/ca.po
odoo_addons/website_product_share/i18n/de.po
odoo_addons/website_product_share/i18n/el_GR.po
odoo_addons/website_product_share/i18n/es.po
odoo_addons/website_product_share/i18n/fr.po
odoo_addons/website_product_share/i18n/it.po
odoo_addons/website_product_share/i18n/pt_BR.po
odoo_addons/website_product_share/i18n/sl.po
odoo_addons/website_product_share/static/description/icon.png
odoo_addons/website_product_share/views/website_product.xml
odoo8_addon_website_product_share-8.0.1.0.0.99.dev10.dist-info/METADATA
odoo8_addon_website_product_share-8.0.1.0.0.99.dev10.dist-info/WHEEL
odoo8_addon_website_product_share-8.0.1.0.0.99.dev10.dist-info/namespace_packages.txt
odoo8_addon_website_product_share-8.0.1.0.0.99.dev10.dist-info/top_level.txt
odoo8_addon_website_product_share-8.0.1.0.0.99.dev10.dist-info/RECORD
